taas_api/__init__.py
taas_api/client.py
taas_api/data.py
taas_api/enums.py
taas_api_client-1.2.9.dist-info/licenses/LICENSE
taas_api_client-1.2.9.dist-info/METADATA
taas_api_client-1.2.9.dist-info/WHEEL
taas_api_client-1.2.9.dist-info/top_level.txt
taas_api_client-1.2.9.dist-info/RECORD
