Metadata-Version: 2.4
Name: taas-api-client
Version: 1.2.9
Summary: API client to interact with the TAAS web API
Author-email: Tread Labs <ops@tread.fi>
Project-URL: Homepage, https://github.com/tread-labs-public/taas-api-client
Project-URL: Bug Tracker, https://github.com/tread-labs-public/taas-api-client/issues
Classifier: Programming Language :: Python :: 3
Classifier: License :: OSI Approved :: MIT License
Classifier: Operating System :: OS Independent
Requires-Python: >=3.7
License-File: LICENSE
Dynamic: license-file
